.gitignore
CHANGELOG
MANIFEST.in
README.rst
rawgithub.ini
setup.py
rawgithub/__init__.py
rawgithub/views.py
rawgithub.egg-info/PKG-INFO
rawgithub.egg-info/SOURCES.txt
rawgithub.egg-info/dependency_links.txt
rawgithub.egg-info/entry_points.txt
rawgithub.egg-info/not-zip-safe
rawgithub.egg-info/requires.txt
rawgithub.egg-info/top_level.txt