Metadata-Version: 1.1
Name: rawgithub
Version: 0.1
Summary: rawgithub
Home-page: https://github.com/diecutter/rawgithub
Author: Rémy HUBSCHER
Author-email: hubscher.remy@gmail.com
License: UNKNOWN
Keywords: web services
Platform: UNKNOWN
Classifier: Programming Language :: Python
Classifier: Framework :: Pylons
Classifier: Topic :: Internet :: WWW/HTTP
Classifier: Topic :: Internet :: WWW/HTTP :: WSGI :: Application
